channels_api/__init__.py
channels_api/bindings.py
channels_api/decorators.py
channels_api/mixins.py
channels_api/permissions.py
channels_api/settings.py
channels_api/urls.py
channels_api/templates/debugger/index.html
channels_api-0.4.0.dist-info/DESCRIPTION.rst
channels_api-0.4.0.dist-info/METADATA
channels_api-0.4.0.dist-info/RECORD
channels_api-0.4.0.dist-info/WHEEL
channels_api-0.4.0.dist-info/metadata.json
channels_api-0.4.0.dist-info/top_level.txt
tests/__init__.py
tests/models.py
tests/routing.py
tests/test_bindings.py
tests/test_settings.py
tests/migrations/0001_initial.py
tests/migrations/__init__.py
