Metadata-Version: 2.0
Name: channels-api
Version: 0.4.0
Summary: Helps build a RESTful API on top of WebSockets using channels.
Home-page: https://github.com/linuxlewis/channels-api
Author: Sam Bolgert
Author-email: sbolgert@gmail.com
License: BSD
Platform: UNKNOWN
Classifier: Programming Language :: Python :: 3
Classifier: Programming Language :: Python :: 3.4
Classifier: Programming Language :: Python :: 3.5
Classifier: Programming Language :: Python :: 3.6
Requires-Dist: Django (>=1.8)
Requires-Dist: channels (>=0.17)
Requires-Dist: djangorestframework (>=3.0)
